google_tr_async/__init__.py
google_tr_async/google_tr_async.py
google_tr_async_free-0.0.2.dist-info/LICENSE
google_tr_async_free-0.0.2.dist-info/METADATA
google_tr_async_free-0.0.2.dist-info/WHEEL
google_tr_async_free-0.0.2.dist-info/top_level.txt
google_tr_async_free-0.0.2.dist-info/RECORD
