Metadata-Version: 2.1
Name: google-tr-async-free
Version: 0.0.2
Summary: google trnaslate async for free
Home-page: http://github.com/ffreemt/google-tr-async-free
Author: mikeee
License: MIT License
Download-URL: https://github.com/ffreemt/google-tr-free/archive/v_0.0.2.tar.gz
Keywords: machine translation,free,scraping
Platform: UNKNOWN
Classifier: Development Status :: 3 - Alpha
Classifier: Intended Audience :: Developers
Classifier: Programming Language :: Python :: 3
Classifier: Programming Language :: Python :: 3.6
Classifier: License :: OSI Approved :: MIT License
Requires-Dist: httpx
Requires-Dist: js2py
Requires-Dist: loguru
